LICENSE
MANIFEST.in
README.md
setup.py
bin/pianoplayer
pianoplayer/__init__.py
pianoplayer/hand.py
pianoplayer/scorereader.py
pianoplayer/utils.py
pianoplayer/vkeyboard.py
pianoplayer/wavegenerator.py
pianoplayer.egg-info/PKG-INFO
pianoplayer.egg-info/SOURCES.txt
pianoplayer.egg-info/dependency_links.txt
pianoplayer.egg-info/requires.txt
pianoplayer.egg-info/top_level.txt
scores/bach_airgstring.xml
scores/bach_invention4.xml
scores/bach_joy.xml
scores/bach_prelude.xml
scores/clayderman_ladyd.xml
scores/couperin_baricades.xml
scores/mozart_sonfacile.xml
scores/pachelbel_canon.xml
scores/test_chords.xml
scores/test_octaves.xml
scores/test_scales.xml