Metadata-Version: 2.1
Name: pianoplayer
Version: 2.2.1
Summary: Automatic piano fingering generator. Finds and shows in 3D the best fingering combination to play a score.
Home-page: https://github.com/marcomusy/pianoplayer
Author: Marco Musy
Author-email: marco.musy@gmail.com
License: MIT
Keywords: piano fingering
Classifier: Intended Audience :: Science/Research
Classifier: Intended Audience :: Education
Classifier: Programming Language :: Python
Classifier: License :: OSI Approved :: MIT License
Classifier: Topic :: Scientific/Engineering :: Visualization
Classifier: Topic :: Scientific/Engineering :: Information Analysis
License-File: LICENSE
